lektor_atom.py
lektor_atom-0.4.0.dist-info/METADATA
lektor_atom-0.4.0.dist-info/WHEEL
lektor_atom-0.4.0.dist-info/entry_points.txt
lektor_atom-0.4.0.dist-info/top_level.txt
lektor_atom-0.4.0.dist-info/RECORD
