Metadata-Version: 2.1
Name: lektor-atom
Version: 0.4.0
Summary: Lektor plugin that generates Atom feeds.
Home-page: https://github.com/lektor/lektor-atom
Author: A. Jesse Jiryu Davis
Author-email: jesse@emptysquare.net
License: MIT
Keywords: Lektor plugin static-site blog atom rss
Platform: UNKNOWN
Classifier: Environment :: Plugins
Classifier: Environment :: Web Environment
Classifier: Framework :: Lektor
Classifier: Intended Audience :: Developers
Classifier: License :: OSI Approved :: MIT License
Requires-Dist: MarkupSafe
Requires-Dist: feedgenerator
